setup.py
slackbotjira/__init__.py
slackbotjira/slackbotjira.py
slackbotjira.egg-info/PKG-INFO
slackbotjira.egg-info/SOURCES.txt
slackbotjira.egg-info/dependency_links.txt
slackbotjira.egg-info/not-zip-safe
slackbotjira.egg-info/requires.txt
slackbotjira.egg-info/top_level.txt