Metadata-Version: 1.0
Name: slackbotjira
Version: 0.2
Summary: Slackbot JIRA Plugin
Home-page: tbd
Author: Kyle Varga
Author-email: slackbot-jira@kylevarga.com
License: MIT
Platform: UNKNOWN
